CHANGES.rst
LICENSE
README.md
setup.py
docs/About.rst
src/senaite/__init__.py
src/senaite.app.supermodel.egg-info/PKG-INFO
src/senaite.app.supermodel.egg-info/SOURCES.txt
src/senaite.app.supermodel.egg-info/dependency_links.txt
src/senaite.app.supermodel.egg-info/entry_points.txt
src/senaite.app.supermodel.egg-info/namespace_packages.txt
src/senaite.app.supermodel.egg-info/not-zip-safe
src/senaite.app.supermodel.egg-info/requires.txt
src/senaite.app.supermodel.egg-info/top_level.txt
src/senaite/app/__init__.py
src/senaite/app/supermodel/__init__.py
src/senaite/app/supermodel/configure.zcml
src/senaite/app/supermodel/decorators.py
src/senaite/app/supermodel/interfaces.py
src/senaite/app/supermodel/model.py