Metadata-Version: 2.1
Name: senaite.app.supermodel
Version: 2.6.0
Summary: A beautiful content wrapper for SENAITE that you will love
Home-page: https://github.com/senaite/senaite.app.supermodel
Author: SENAITE Professional Service Providers
Author-email: senaite@senaite.com
License: GPLv2
Platform: UNKNOWN
Classifier: Framework :: Plone
Classifier: Framework :: Zope2
Classifier: Programming Language :: Python
Classifier: Development Status :: 5 - Production/Stable
Classifier: License :: OSI Approved :: GNU General Public License v2 (GPLv2)
Provides-Extra: test
